biyam/__init__.py
biyam/biyam.py
biyam/rpcmanager.py
biyam/static/0.js
biyam/static/0.js.map
biyam/static/1.js
biyam/static/1.js.map
biyam/static/10.js
biyam/static/10.js.map
biyam/static/100.js
biyam/static/100.js.map
biyam/static/101.js
biyam/static/101.js.map
biyam/static/102.js
biyam/static/102.js.map
biyam/static/103.js
biyam/static/103.js.map
biyam/static/104.js
biyam/static/104.js.map
biyam/static/105.js
biyam/static/105.js.map
biyam/static/106.js
biyam/static/106.js.map
biyam/static/107.js
biyam/static/107.js.map
biyam/static/108.js
biyam/static/108.js.map
biyam/static/109.js
biyam/static/109.js.map
biyam/static/11.js
biyam/static/11.js.map
biyam/static/110.js
biyam/static/110.js.map
biyam/static/111.js
biyam/static/111.js.map
biyam/static/112.js
biyam/static/112.js.map
biyam/static/113.js
biyam/static/113.js.map
biyam/static/114.js
biyam/static/114.js.map
biyam/static/115.js
biyam/static/115.js.map
biyam/static/116.js
biyam/static/116.js.map
biyam/static/117.js
biyam/static/117.js.map
biyam/static/118.js
biyam/static/118.js.map
biyam/static/119.js
biyam/static/119.js.map
biyam/static/12.js
biyam/static/12.js.map
biyam/static/120.js
biyam/static/120.js.map
biyam/static/121.js
biyam/static/121.js.map
biyam/static/122.js
biyam/static/122.js.map
biyam/static/123.js
biyam/static/123.js.map
biyam/static/124.js
biyam/static/124.js.map
biyam/static/125.js
biyam/static/125.js.map
biyam/static/126.js
biyam/static/126.js.map
biyam/static/127.js
biyam/static/127.js.map
biyam/static/128.js
biyam/static/128.js.map
biyam/static/13.js
biyam/static/13.js.map
biyam/static/14.js
biyam/static/14.js.map
biyam/static/15.js
biyam/static/15.js.map
biyam/static/16.js
biyam/static/16.js.map
biyam/static/17.js
biyam/static/17.js.map
biyam/static/18.js
biyam/static/18.js.map
biyam/static/19.js
biyam/static/19.js.map
biyam/static/2.js
biyam/static/2.js.map
biyam/static/20.js
biyam/static/20.js.map
biyam/static/21.js
biyam/static/21.js.map
biyam/static/22.js
biyam/static/22.js.map
biyam-2017.12.22a0.dev1.dist-info/LICENSE.md
biyam-2017.12.22a0.dev1.dist-info/METADATA
biyam-2017.12.22a0.dev1.dist-info/WHEEL
biyam-2017.12.22a0.dev1.dist-info/top_level.txt
biyam-2017.12.22a0.dev1.dist-info/RECORD
